affen/__init__.py
affen/api.py
affen/utils.py
affen-0.2.1.dist-info/WHEEL
affen-0.2.1.dist-info/METADATA
affen-0.2.1.dist-info/RECORD
