Metadata-Version: 2.1
Name: affen
Version: 0.2.1
Summary: plone.restapi for Humans™
License: MPL-2.0
Author-email: Chris Wesseling <Chris.Wesseling@cwi.nl>
Requires-Python: >=3.7
Classifier: Development Status :: 4 - Beta
Classifier: Framework :: Plone
Classifier: Intended Audience :: Developers
Requires-Dist: requests~=2.26
Project-URL: homepage, https://github.com/CharString/affen
